<?xml version="1.0" encoding="UTF-8"?>
<!DOCTYPE xml>

<menu-set name="系统模块" code="system">
	<menuItems>
		<menu-item text="人员管理" code="personnel" iconCls="Userhome">
			<children>
				<menu-item text="用户列表" code="user" iconCls="User"
					view="app.view.user.UserList" />
				<menu-item text="角色列表" code="role" iconCls="Userkey"
					view="app.view.role.RoleList" />
				<menu-item text="模板管理" code="cmstemplate" iconCls="Userkey"
					view="app.view.cms.Template" />
			</children>
		</menu-item>

		<menu-item text="参数设置" code="setting" iconCls="Cog">
			<children>
				<menu-item text="系统参数" code="system" iconCls="Cog"
					view="app.view.role.List" />
			</children>
		</menu-item>

	</menuItems>
</menu-set>